{
  "meta": {
    "units": "ft",
    "cell_size": 1.0
  },
  "space": {
    "width": 30,
    "height": 40
  },
  "entry": {
    "wall": "south",
    "offset": 13.0,
    "width": 5.0
  },
  "exit": {
    "wall": "north",
    "offset": 18.0,
    "width": 5.0
  },
  "modules": [
    {
      "id": "m1",
      "type": "physical_experience",
      "x": 3.0,
      "y": 5.0,
      "w": 6,
      "h": 6,
      "rot": 90
    },
    {
      "id": "m2",
      "type": "physical_experience",
      "x": 9.0,
      "y": 24.0,
      "w": 10,
      "h": 4,
      "rot": 180
    },
    {
      "id": "m3",
      "type": "sample_station",
      "x": 8.0,
      "y": 16.0,
      "w": 4,
      "h": 4,
      "rot": 90
    },
    {
      "id": "m4",
      "type": "sample_station",
      "x": 21.0,
      "y": 6.0,
      "w": 6,
      "h": 6,
      "rot": 0
    },
    {
      "id": "m5",
      "type": "merch_display",
      "x": 14.0,
      "y": 4.0,
      "w": 6,
      "h": 2,
      "rot": 270
    },
    {
      "id": "m6",
      "type": "digital_display",
      "x": 19.0,
      "y": 19.0,
      "w": 10,
      "h": 10,
      "rot": 270
    }
  ]
}